browser/__init__.py
browser/pool.py
clipsight-0.2.1.dist-info/licenses/LICENSE
crawler/__init__.py
crawler/google_images.py
pipeline/__init__.py
pipeline/image_processor.py
search/__init__.py
search/similar_images.py
storage/__init__.py
storage/minio_client.py
storage/minio_storage.py
worker/__init__.py
worker/consumer.py
worker/main.py
clipsight-0.2.1.dist-info/METADATA
clipsight-0.2.1.dist-info/WHEEL
clipsight-0.2.1.dist-info/entry_points.txt
clipsight-0.2.1.dist-info/top_level.txt
clipsight-0.2.1.dist-info/RECORD
