Metadata-Version: 2.4
Name: clipsight
Version: 0.2.1
Summary: A distributed image crawling system based on Playwright
Home-page: https://gitee.com/duckweeds7/clip-sight
Author: duckweeds7
Author-email: duckweeds7@gmail.com
Project-URL: Bug Tracker, https://gitee.com/duckweeds7/clip-sight/issues
Project-URL: Documentation, https://gitee.com/duckweeds7/clip-sight/wikis
Project-URL: Source Code, https://gitee.com/duckweeds7/clip-sight
Classifier: Development Status :: 4 - Beta
Classifier: Intended Audience :: Developers
Classifier: License :: OSI Approved :: MIT License
Classifier: Operating System :: OS Independent
Classifier: Programming Language :: Python :: 3
Classifier: Programming Language :: Python :: 3.8
Classifier: Programming Language :: Python :: 3.9
Classifier: Programming Language :: Python :: 3.10
Classifier: Programming Language :: Python :: 3.11
Classifier: Topic :: Software Development :: Libraries :: Python Modules
Classifier: Topic :: Internet :: WWW/HTTP :: Dynamic Content
Classifier: Topic :: Multimedia :: Graphics
Requires-Python: >=3.8
License-File: LICENSE
Requires-Dist: fastapi>=0.68.1
Requires-Dist: uvicorn>=0.15.0
Requires-Dist: python-dotenv>=0.19.0
Requires-Dist: loguru>=0.5.3
Requires-Dist: playwright>=1.20.0
Requires-Dist: minio>=7.1.0
Requires-Dist: redis>=4.0.2
Requires-Dist: elasticsearch>=7.17.0
Requires-Dist: celery>=5.2.0
Requires-Dist: aiohttp>=3.8.0
Requires-Dist: pillow>=8.3.0
Requires-Dist: numpy>=1.21.0
Requires-Dist: scikit-learn>=0.24.0
Requires-Dist: python-multipart>=0.0.5
Requires-Dist: pydantic>=1.8.0
Requires-Dist: httpx>=0.23.0
Requires-Dist: tenacity>=8.0.0
Requires-Dist: prometheus-client>=0.12.0
Requires-Dist: opencv-python>=4.5.0
Requires-Dist: tensorflow>=2.8.0
Requires-Dist: transformers>=4.15.0
Requires-Dist: torch>=1.10.0
Requires-Dist: torchvision>=0.11.0
Requires-Dist: faiss-cpu>=1.7.0
Requires-Dist: sentence-transformers>=2.2.0
Requires-Dist: beautifulsoup4>=4.9.0
Requires-Dist: lxml>=4.9.0
Requires-Dist: requests>=2.26.0
Requires-Dist: aiofiles>=0.8.0
Requires-Dist: python-jose>=3.3.0
Requires-Dist: passlib>=1.7.4
Requires-Dist: bcrypt>=3.2.0
Requires-Dist: pytest>=6.2.5
Requires-Dist: pytest-asyncio>=0.16.0
Requires-Dist: pytest-cov>=2.12.0
Requires-Dist: black>=21.7b0
Requires-Dist: isort>=5.9.0
Requires-Dist: flake8>=3.9.0
Requires-Dist: mypy>=0.910
Requires-Dist: pre-commit>=2.15.0
Requires-Dist: setuptools>=45.0.0
Requires-Dist: wheel>=0.37.0
Requires-Dist: twine>=3.4.0
Requires-Dist: build>=0.7.0
Requires-Dist: setuptools_scm>=6.2.0
Dynamic: author
Dynamic: author-email
Dynamic: classifier
Dynamic: description
Dynamic: description-content-type
Dynamic: home-page
Dynamic: license-file
Dynamic: project-url
Dynamic: requires-dist
Dynamic: requires-python
Dynamic: summary
